Metadata-Version: 2.1
Name: text2digits
Version: 0.1.0
Summary: A small library to convert text numbers to digits in a string
Home-page: https://github.com/careless25/text2digits
Author: Shail Choksi
Author-email: choksishail@gmail.com
License: UNKNOWN
Project-URL: Funding, https://www.paypal.me/careless25
Project-URL: Source, https://github.com/careless25/text2digits
Keywords: text2numbers words2numbers digits numbers
Platform: UNKNOWN
Classifier: Programming Language :: Python :: 3
Classifier: License :: OSI Approved :: MIT License
Classifier: Operating System :: OS Independent
